setup.py
ac_gb_distributions/Binomialdistribution.py
ac_gb_distributions/Gaussiandistribution.py
ac_gb_distributions/Generaldistribution.py
ac_gb_distributions/__init__.py
ac_gb_distributions.egg-info/PKG-INFO
ac_gb_distributions.egg-info/SOURCES.txt
ac_gb_distributions.egg-info/dependency_links.txt
ac_gb_distributions.egg-info/not-zip-safe
ac_gb_distributions.egg-info/top_level.txt